openclean_geo/__init__.py
openclean_geo/version.py
openclean_geo/address/usstreet.py
openclean_geo/spatial/wkt.py
openclean_geo-0.1.0.dist-info/LICENSE
openclean_geo-0.1.0.dist-info/METADATA
openclean_geo-0.1.0.dist-info/WHEEL
openclean_geo-0.1.0.dist-info/top_level.txt
openclean_geo-0.1.0.dist-info/RECORD
